verilog/Register.v
module RegisterFile(BusA, BusB, BusW, RA, RB, RW, RegWr, Clk, Rst,
regOut0,regOut1,regOut2,regOut3,regOut4,regOut5,regOut6,regOut7,
regOut8,regOut9,regOut10,regOut11,regOut12,regOut13,regOut14,regOut15,
regOut16,regOut17,regOut18,regOut19,regOut20,regOut21,regOut22,regOut23,
regOut24,regOut25,regOut26,regOut27,regOut28,regOut29,regOut30,regOut31
);

//Inputs: Read Register 1, Read Register 2, Write Register (5bits), Write Data (32bits), Write Control
	output reg [31:0] BusA, BusB;  //data to read
	input [4:0] RA, RB, RW;  //read addr A, read addr B, write addr
	input [31:0] BusW;  //data to write
	input RegWr;  //write ctrl
	input Clk, Rst;
	
	reg [31:0] registers [31:0];

	output [31:0] regOut0;
	output [31:0] regOut1;
	output [31:0] regOut2;
	output [31:0] regOut3;
	output [31:0] regOut4;
	output [31:0] regOut5;
	output [31:0] regOut6;
	output [31:0] regOut7;
	output [31:0] regOut8;
	output [31:0] regOut9;
	output [31:0] regOut10;
	output [31:0] regOut11;
	output [31:0] regOut12;
	output [31:0] regOut13;
	output [31:0] regOut14;
	output [31:0] regOut15;
	output [31:0] regOut16;
	output [31:0] regOut17;
	output [31:0] regOut18;
	output [31:0] regOut19;
	output [31:0] regOut20;
	output [31:0] regOut21;
	output [31:0] regOut22;
	output [31:0] regOut23;
	output [31:0] regOut24;
	output [31:0] regOut25;
	output [31:0] regOut26;
	output [31:0] regOut27;
	output [31:0] regOut28;
	output [31:0] regOut29;
	output [31:0] regOut30;
	output [31:0] regOut31;

	assign regOut0 = registers[0];
	assign regOut1 = registers[1];
	assign regOut2 = registers[2];
	assign regOut3 = registers[3];
	assign regOut4 = registers[4];
	assign regOut5 = registers[5];
	assign regOut6 = registers[6];
	assign regOut7 = registers[7];
	assign regOut8 = registers[8];
	assign regOut9 = registers[9];
	assign regOut10 = registers[10];
	assign regOut11 = registers[11];
	assign regOut12 = registers[12];
	assign regOut13 = registers[13];
	assign regOut14 = registers[14];
	assign regOut15 = registers[15];
	assign regOut16 = registers[16];
	assign regOut17 = registers[17];
	assign regOut18 = registers[18];
	assign regOut19 = registers[19];
	assign regOut20 = registers[20];
	assign regOut21 = registers[21];
	assign regOut22 = registers[22];
	assign regOut23 = registers[23];
	assign regOut24 = registers[24];
	assign regOut25 = registers[25];
	assign regOut26 = registers[26];
	assign regOut27 = registers[27];
	assign regOut28 = registers[28];
	assign regOut29 = registers[29];
	assign regOut30 = registers[30];
	assign regOut31 = registers[31];
	
	integer i, j;
	
	initial begin //initialize all register values to 0
		for(i = 0; i < 32; i = i + 1) begin
				registers[i] <= 0;
		end
	end
	
	always begin
		@(posedge Clk) begin
			if (RegWr && RW != 0) begin //$0 must remain unchanged as 0
				registers[RW] <= BusW;
			end
			else if (Rst) begin
				for(j = 0; j < 32; j = j + 1) 
					registers[j] <= 0;
			end
		end
		
		@(negedge Clk) begin
			BusA <= registers[RA];
			BusB <= registers[RB];
		end
	end
	
endmodule

verilog/Register_tb.v
`timescale 1 ns / 1 ns

module tb();

	parameter tck = 10; // clock tick
  
	reg clk, rst;
	reg [31:0]W;
	reg [4:0] RA, RB, RW;
	reg wrn;
  
	wire [31:0] A, B;
	
	integer seed = 1;
	
	/*
		wire [31:0] regOut0;
		wire [31:0] regOut1;
		wire [31:0] regOut2;
		wire [31:0] regOut3;
		wire [31:0] regOut4;
		wire [31:0] regOut5;
		wire [31:0] regOut6;
		wire [31:0] regOut7;
		wire [31:0] regOut8;
		wire [31:0] regOut9;
		wire [31:0] regOut10;
		wire [31:0] regOut11;
		wire [31:0] regOut12;
		wire [31:0] regOut13;
		wire [31:0] regOut14;
		wire [31:0] regOut15;
		wire [31:0] regOut16;
		wire [31:0] regOut17;
		wire [31:0] regOut18;
		wire [31:0] regOut19;
		wire [31:0] regOut20;
		wire [31:0] regOut21;
		wire [31:0] regOut22;
		wire [31:0] regOut23;
		wire [31:0] regOut24;
		wire [31:0] regOut25;
		wire [31:0] regOut26;
		wire [31:0] regOut27;
		wire [31:0] regOut28;
		wire [31:0] regOut29;
		wire [31:0] regOut30;
		wire [31:0] regOut31;
	*/
	
	RegisterFile dut
	(
		.BusA(A), 
		.BusB(B),
		.BusW(W),
		.RA(RA),
		.RB(RB),
		.RW(RW),
		.RegWr(wrn),
		.Clk(clk),
		.Rst(rst),	
	
	/*
		.regOut0(regOut0),
		.regOut1(regOut1),
		.regOut2(regOut2),
		.regOut3(regOut3),
		.regOut4(regOut4),
		.regOut5(regOut5),
		.regOut6(regOut6),
		.regOut7(regOut7),
		.regOut8(regOut8),
		.regOut9(regOut9),
		.regOut10(regOut10),
		.regOut11(regOut11),
		.regOut12(regOut12),
		.regOut13(regOut13),
		.regOut14(regOut14),
		.regOut15(regOut15),
		.regOut16(regOut16),
		.regOut17(regOut17),
		.regOut18(regOut18),
		.regOut19(regOut19),
		.regOut20(regOut20),
		.regOut21(regOut21),
		.regOut22(regOut22),
		.regOut23(regOut23),
		.regOut24(regOut24),
		.regOut25(regOut25),
		.regOut26(regOut26),
		.regOut27(regOut27),
		.regOut28(regOut28),
		.regOut29(regOut29),
		.regOut30(regOut30),
		.regOut31(regOut31)
	*/
	);
	  
	integer num_iter = 0 ;
	always #(tck/2) clk <= ~clk; // clocking device
	  
	initial begin
		$dumpfile("Register_ah.vcd"); 
		$dumpvars (-1, dut);
	end

	initial begin
		clk = 0; rst = 0; wrn = 0;
		RA  = 4'd0;
		RB  = 4'd0;
		RW  = 4'd0;
		W = 32'd0;  
	end
	
	always @(posedge clk) begin
		RA  = $random(seed);
		RB  = $random(seed);
		RW  = $random(seed);
		W   = $random(seed);
		wrn = $random(seed);

		// limit random reset to every 10 cycles
		// to make results more readable
		if (num_iter % 10 == 1) begin
			rst = $random(seed);	
		end
		else begin
			rst = 0;
		end
		
		++ num_iter;
	end
	
	always @(negedge clk) begin
		if (num_iter > 5000)
			$finish;
	end
  
endmodule

verilog/Register_ah.vcd
$date
	Fri Apr  6 20:18:09 2018
$end
$version
	Icarus Verilog
$end
$timescale
	1ns
$end
$scope module tb $end
$scope module dut $end
$var wire 32 ! BusW [31:0] $end
$var wire 1 " Clk $end
$var wire 5 # RA [4:0] $end
$var wire 5 $ RB [4:0] $end
$var wire 5 % RW [4:0] $end
$var wire 1 & RegWr $end
$var wire 1 ' Rst $end
$var wire 32 ( regOut0 [31:0] $end
$var wire 32 ) regOut1 [31:0] $end
$var wire 32 * regOut10 [31:0] $end
$var wire 32 + regOut11 [31:0] $end
$var wire 32 , regOut12 [31:0] $end
$var wire 32 - regOut13 [31:0] $end
$var wire 32 . regOut14 [31:0] $end
$var wire 32 / regOut15 [31:0] $end
$var wire 32 0 regOut16 [31:0] $end
$var wire 32 1 regOut17 [31:0] $end
$var wire 32 2 regOut18 [31:0] $end
$var wire 32 3 regOut19 [31:0] $end
$var wire 32 4 regOut2 [31:0] $end
$var wire 32 5 regOut20 [31:0] $end
$var wire 32 6 regOut21 [31:0] $end
$var wire 32 7 regOut22 [31:0] $end
$var wire 32 8 regOut23 [31:0] $end
$var wire 32 9 regOut24 [31:0] $end
$var wire 32 : regOut25 [31:0] $end
$var wire 32 ; regOut26 [31:0] $end
$var wire 32 < regOut27 [31:0] $end
$var wire 32 = regOut28 [31:0] $end
$var wire 32 > regOut29 [31:0] $end
$var wire 32 ? regOut3 [31:0] $end
$var wire 32 @ regOut30 [31:0] $end
$var wire 32 A regOut31 [31:0] $end
$var wire 32 B regOut4 [31:0] $end
$var wire 32 C regOut5 [31:0] $end
$var wire 32 D regOut6 [31:0] $end
$var wire 32 E regOut7 [31:0] $end
$var wire 32 F regOut8 [31:0] $end
$var wire 32 G regOut9 [31:0] $end
$var reg 32 H BusA [31:0] $end
$var reg 32 I BusB [31:0] $end
$var integer 32 J i [31:0] $end
$var integer 32 K j [31:0] $end
$upscope $end
$upscope $end
$enddefinitions $end
#0
$dumpvars
b100000 K
bx J
bx I
bx H
b0 G
b0 F
b0 E
b0 D
b0 C
b0 B
b0 A
b0 @
b0 ?
b0 >
b0 =
b0 <
b0 ;
b0 :
b0 9
b0 8
b0 7
b0 6
b0 5
b0 4
b0 3
b0 2
b0 1
b0 0
b0 /
b0 .
b0 -
b0 ,
b0 +
b0 *
b0 )
b0 (
0'
0&
b0 %
b0 $
b0 #
0"
b0 !
$end
#5
b10101110000100110000110001011100 !
b110 %
b11000 $
1"
#10
b0 I
b0 H
0"
#15
1'
1&
b1100001110101110110011111000011 !
b10011 %
b110 $
b111 #
1"
#20
0"
#25
b1100001110101110110011111000011 3
0'
b10101110110110100011000001011101 !
b101 %
b11110 $
b1001 #
1"
#30
0"
#35
b10101110110110100011000001011101 C
b11100100110111000000001011001001 !
b11100 %
b1111 $
b1110 #
1"
#40
0"
#45
b11100100110111000000001011001001 =
b10001000110010001011000000010001 !
b11111 %
b1100 $
b11100 #
1"
#50
b11100100110111000000001011001001 H
0"
#55
b10001000110010001011000000010001 A
0&
b10011000110000110111001000110001 !
b10001 $
b0 #
1"
#60
b0 H
0"
#65
1&
b1011101011011010101100010111 !
b101 %
b10101 $
b1010 #
1"
#70
0"
#75
b1011101011011010101100010111 C
0&
b1111011001100010101101111110110 !
b11100 %
b10111 $
b11 #
1"
#80
0"
#85
b10100000000101000100000101 !
b1110 %
b111 $
b1000 #
1"
#90
0"
#95
b1001110001011101101001110011100 !
b11001 %
b1110 $
b100 #
1"
#100
0"
#105
1&
b1110010101111110100000111100101 !
b11000 %
b1011 $
b1011 #
1"
#110
0"
#115
b1110010101111110100000111100101 9
b10010000000000000011001000100000 !
b1011 %
b1110 $
b111 #
1"
#120
0"
#125
b10010000000000000011001000100000 +
b11110000000011101010001011100000 !
b11000 %
b11 $
b1 #
1"
#130
0"
#135
b11110000000011101010001011100000 9
b1110001000000101100101111100010 !
b11111 %
b101 $
b10111 #
1"
#140
b1011101011011010101100010111 I
0"
#145
b1110001000000101100101111100010 A
b11010110111101100101110010101101 !
b10 %
b1010 $
b100 #
1"
#150
b0 I
0"
#155
b11010110111101100101110010101101 4
0&
b10000110100010001101011000001101 !
b1011 %
b10 $
b11100 #
1"
#160
b11010110111101100101110010101101 I
b11100100110111000000001011001001 H
0"
#165
b1101001010001101000110111010010 !
b10000 %
b1011 $
b11111 #
1"
#170
b10010000000000000011001000100000 I
b1110001000000101100101111100010 H
0"
#175
b1110011100010100101100111100111 !
b11100 %
b10 $
b100 #
1"
#180
b11010110111101100101110010101101 I
b0 H
0"
#185
1&
b1110110010010111000010111101100 !
b1011 %
b11100 $
b1000 #
1"
#190
b11100100110111000000001011001001 I
0"
#195
b1110110010010111000010111101100 +
b10101110000111101101000001011100 !
b11110 %
b10011 $
b11000 #
1"
#200
b1100001110101110110011111000011 I
b11110000000011101010001011100000 H
0"
#205
b10101110000111101101000001011100 @
0&
b10000001001001110111000000000010 !
b10011 %
b11011 $
b110 #
1"
#210
b0 I
b0 H
0"
#215
1'
b10011110010010111010101000111100 !
b1101 %
b11101 $
b0 #
1"
#220
0"
#225
b0 A
b0 @
b0 =
b0 9
b0 3
b0 +
b0 C
b0 4
0'
b1000100001001110000011110001000 !
b11110 %
b1001 $
b11110 #
b100000 J
1"
#230
0"
#235
1&
b1101010000001101010010111010100 !
b10010 %
b10100 $
b111 #
1"
#240
0"
#245
b1101010000001101010010111010100 2
0&
b11001010100100110100111010010101 !
b11 %
b11011 $
b10111 #
1"
#250
0"
#255
1&
b10011000001111110101001000110000 !
b1111 %
b10101 $
b10110 #
1"
#260
0"
#265
b10011000001111110101001000110000 /
b11011101100000000100000110 !
b10110 %
b10000 $
b11 #
1"
#270
0"
#275
b11011101100000000100000110 7
0&
b11110000110100111111110011100001 !
b10 %
b10011 $
b1001 #
1"
#280
0"
#285
1&
b11010011110111111110000010100111 !
b1110 $
b11000 #
1"
#290
0"
#295
b11010011110111111110000010100111 4
0&
b11101010110011110111111011010101 !
b11111 %
b110 $
b11101 #
1"
#300
0"
#305
b11111001101011101100001011110011 !
b10 $
b110 #
1"
#310
b11010011110111111110000010100111 I
0"
#315
1'
1&
b1001011001110110001100110010110 !
b10011 %
b10001 $
b1001 #
1"
#320
b0 I
0"
#325
b1001011001110110001100110010110 3
0'
b1100001101001001100100011000 !
b1 %
b110 $
b11111 #
1"
#330
0"
#335
b1100001101001001100100011000 )
b11010111101000010000001010101111 !
b1111 %
b10 $
b10 #
1"
#340
b11010011110111111110000010100111 I
b11010011110111111110000010100111 H
0"
#345
b11010111101000010000001010101111 /
0&
b1100111011010110110110111001110 !
b10110 %
b1100 $
b10100 #
1"
#350
b0 I
b0 H
0"
#355
1&
b1010111100100110101111110101111 !
b11100 %
b10100 $
b1000 #
1"
#360
0"
#365
b1010111100100110101111110101111 =
0&
b10101111011101000000101001011110 !
b111 %
b11110 $
b110 #
1"
#370
0"
#375
1&
b10010001010111001100111000100010 !
b1000 %
b1000 $
b10100 #
1"
#380
0"
#385
b10010001010111001100111000100010 F
0&
b10110100011110011110001001101000 !
b10100 %
b1110 $
b10101 #
1"
#390
0"
#395
1&
b11111000101001111110010011110001 !
b11100 %
b11 $
b1010 #
1"
#400
0"
#405
b11111000101001111110010011110001 =
0&
b10011111001000110100100100111 !
b10110 %
b11000 $
b11000 #
1"
#410
0"
#415
1&
b11010100111111101100011010101001 !
b1 %
b11010 $
b10111 #
1"
#420
0"
#425
b11010100111111101100011010101001 )
0&
b10100011111001001100111001000111 !
b11011 %
b0 $
b10001 #
1"
#430
0"
#435
b100001111110101010100001000 !
b1101 %
b1000 $
1"
#440
b10010001010111001100111000100010 I
0"
#445
b1110111101011111101001111101111 !
b10100 %
b0 $
b11011 #
1"
#450
b0 I
0"
#455
1&
b11001100011010001110100110011 !
b11010 %
b1100 $
b1100 #
1"
#460
0"
#465
b11001100011010001110100110011 ;
b11101011101101001100100111010 !
b11101 %
b1101 $
b10010 #
1"
#470
b1101010000001101010010111010100 H
0"
#475
b11101011101101001100100111010 >
b1111000100011011010000111110001 !
b1000 %
b1001 $
b1010 #
1"
#480
b0 H
0"
#485
b1111000100011011010000111110001 F
0&
b10111101110101011101110001111011 !
b1100 %
b11001 $
b1110 #
1"
#490
0"
#495
1&
b11000011011000100110000010000110 !
b10100 %
b1100 $
b10010 #
1"
#500
b1101010000001101010010111010100 H
0"
#505
b11000011011000100110000010000110 5
0&
b11000111000010000000010010001110 !
b10110 %
b110 $
b1010 #
1"
#510
b0 H
0"
#515
b101010101011010110000101010101 !
b11101 %
b10 $
b1111 #
1"
#520
b11010011110111111110000010100111 I
b11010111101000010000001010101111 H
0"
#525
b1100010111100101110000111000101 !
b10010 %
b0 $
1"
#530
b0 I
0"
#535
b11011110111011100010011010111101 !
b101 %
b1 $
b1000 #
1"
#540
b11010100111111101100011010101001 I
b1111000100011011010000111110001 H
0"
#545
1&
b10111100000100011101111001111000 !
b11 %
b10110 $
b11000 #
1"
#550
b11011101100000000100000110 I
b0 H
0"
#555
b10111100000100011101111001111000 ?
0&
b11011010010101100001010010110100 !
b10111 %
b1101 $
b110 #
1"
#560
b0 I
0"
#565
b10001100101111101001100100011 !
b11101 %
b0 $
b101 #
1"
#570
0"
#575
b10110001100111001001111001100011 !
b1101 $
b11 #
1"
#580
b10111100000100011101111001111000 H
0"
#585
b1010000010011010100000010 !
b1101 %
b1 $
1"
#590
b11010100111111101100011010101001 I
0"
#595
b10001100110001011101000000011001 !
b10001 %
b11100 $
b1110 #
1"
#600
b11111000101001111110010011110001 I
b0 H
0"
#605
1&
b10111010100111001011100101110 !
b1 %
b11111 $
b10 #
1"
#610
b0 I
b11010011110111111110000010100111 H
0"
#615
b10111010100111001011100101110 )
b10101011110100011101111001010111 !
b1110 %
b1100 $
b0 #
1"
#620
b0 H
0"
#625
b10101011110100011101111001010111 .
b1000101111110011011011110001011 !
b10101 %
b100 $
b11101 #
1"
#630
b11101011101101001100100111010 H
0"
#635
b1000101111110011011011110001011 6
b110001101100001101011101100011 !
b11000 %
b10111 $
b11110 #
1"
#640
b0 H
0"
#645
b110001101100001101011101100011 9
b11001101000111111111101010011010 !
b1011 %
b10010 $
b10110 #
1"
#650
b1101010000001101010010111010100 I
b11011101100000000100000110 H
0"
#655
b11001101000111111111101010011010 +
b10100101000100110101100001001010 !
b11100 %
b1011 $
b10 #
1"
#660
b11001101000111111111101010011010 I
b11010011110111111110000010100111 H
0"
#665
b10100101000100110101100001001010 =
b11010100101000100110100010101001 !
b0 %
b10110 $
b101 #
1"
#670
b11011101100000000100000110 I
b0 H
0"
#675
b11010100101000100110100010101001 (
0&
b101001000100111011000101010010 !
b10111 %
b1000 $
b11100 #
1"
#680
b1111000100011011010000111110001 I
b10100101000100110101100001001010 H
0"
#685
b1111110100010000111100011111 !
b11110 %
b1101 $
b111 #
1"
#690
b0 I
b0 H
0"
#695
b11010101011111111110100010101010 !
b11 %
b1000 $
b1111 #
1"
#700
b1111000100011011010000111110001 I
b11010111101000010000001010101111 H
0"
#705
1&
b100010110111010100011101000101 !
b10110 %
b100 $
b10001 #
1"
#710
b0 I
b0 H
0"
#715
b100010110111010100011101000101 7
1'
0&
b1100101001011111010001111001010 !
b10001 %
b10101 $
b11001 #
1"
#720
b1000101111110011011011110001011 I
0"
#725
b0 >
b0 =
b0 ;
b0 9
b0 7
b0 6
b0 5
b0 3
b0 2
b0 /
b0 .
b0 +
b0 F
b0 ?
b0 4
b0 )
b0 (
0'
b101101111101100000011101011011 !
b10100 %
b1000 $
b1101 #
b100000 J
1"
#730
b0 I
0"
#735
1&
b111000101001000001011101110001 !
b1101 %
b1010 $
b10001 #
1"
#740
0"
#745
b111000101001000001011101110001 -
0&
b10111101100111110110010001111011 !
b11 %
b11000 $
b1101 #
1"
#750
b111000101001000001011101110001 H
0"
#755
b10100110110111111110101001001101 !
b11000 %
b11100 $
b11001 #
1"
#760
b0 H
0"
#765
1&
b100110101001101110000101001101 !
b10111 %
b11111 $
b10010 #
1"
#770
0"
#775
b100110101001101110000101001101 8
0&
b101101001011110111000101011010 !
b1101 %
b110 $
b11010 #
1"
#780
0"
#785
b11011010011001001101010010110100 !
b10010 %
b11100 $
b11000 #
1"
#790
0"
#795
b100000110010111000101101000001 !
b1000 %
b11111 $
b11110 #
1"
#800
0"
#805
1&
b10111011111101101101101001110111 !
b1101 %
b1011 $
b0 #
1"
#810
0"
#815
b10111011111101101101101001110111 -
1'
b10100000000110001101111001000000 !
b10100 %
b1000 $
b10101 #
1"
#820
0"
#825
b10100000000110001101111001000000 5
0'
b1100110110011110101110111001101 !
b11010 %
b11000 $
b10001 #
1"
#830
0"
#835
b1100110110011110101110111001101 ;
b11100010010011010010110011000100 !
b10010 %
b1 $
b11100 #
1"
#840
0"
#845
b11100010010011010010110011000100 2
b11000111010010110101100010001110 !
b11001 %
b111 $
b10100 #
1"
#850
b10100000000110001101111001000000 H
0"
#855
b11000111010010110101100010001110 :
b110100110001001010101101101001 !
b11101 %
b1101 $
b11 #
1"
#860
b10111011111101101101101001110111 I
b0 H
0"
#865
b110100110001001010101101101001 >
b10000100001111111001010000001000 !
b11011 %
b100 $
b10100 #
1"
#870
b0 I
b10100000000110001101111001000000 H
0"
#875
b10000100001111111001010000001000 <
0&
b10100010101010111001100001000101 !
b1 %
b11010 #
1"
#880
b1100110110011110101110111001101 H
0"
#885
b10011110101000111100110000111101 !
b1101 %
b11111 $
b1110 #
1"
#890
b0 H
0"
#895
1&
b1001010010110110000100010010 !
b11101 %
b11001 $
b11111 #
1"
#900
b11000111010010110101100010001110 I
0"
#905
b1001010010110110000100010010 >
b11110000101011111011000011100001 !
b10001 %
b1010 $
b11010 #
1"
#910
b0 I
b1100110110011110101110111001101 H
0"
#915
b11110000101011111011000011100001 1
0&
b1100010100011110010110111000101 !
b11111 %
b1101 $
b10010 #
1"
#920
b10111011111101101101101001110111 I
b11100010010011010010110011000100 H
0"
#925
1&
b1011110011011000111110110111100 !
b10100 %
b110 $
b10000 #
1"
#930
b0 I
b0 H
0"
#935
b1011110011011000111110110111100 5
0&
b10010110111001101001110000101101 !
b11001 %
b1001 $
b1 #
1"
#940
0"
#945
b1111001011010111000100011110 !
b1000 %
b11011 $
b11010 #
1"
#950
b10000100001111111001010000001000 I
b1100110110011110101110111001101 H
0"
#955
b111111111000000001111101111111 !
b10110 %
b1100 #
1"
#960
b0 H
0"
#965
1&
b10111000010000101100011001110000 !
b101 $
b1101 #
1"
#970
b0 I
b10111011111101101101101001110111 H
0"
#975
b10111000010000101100011001110000 7
b1111011011111001001100111110110 !
b11001 %
b111 $
b11010 #
1"
#980
b1100110110011110101110111001101 H
0"
#985
b1111011011111001001100111110110 :
b1101001111111001001111111010011 !
b1000 %
b1011 $
b1100 #
1"
#990
b0 H
0"
#995
b1101001111111001001111111010011 F
0&
b1010001100100001101100010100 !
b11001 %
b11110 $
b1001 #
1"
#1000
0"
#1005
b111011011000110111001101110110 !
b10 %
b1001 $
b11110 #
1"
#1010
0"
#1015
1'
1&
b10010101100011010010001000101011 !
b10111 %
b11011 $
b10100 #
1"
#1020
b10000100001111111001010000001000 I
b1011110011011000111110110111100 H
0"
#1025
b10010101100011010010001000101011 8
0'
b10101110000110001100000101 !
b10101 %
b11000 $
b0 #
1"
#1030
b0 I
b0 H
0"
#1035
b10101110000110001100000101 6
0&
b11110110001100001011000011101100 !
b1110 %
b10001 $
b100 #
1"
#1040
b11110000101011111011000011100001 I
0"
#1045
1&
b10000011100110011110100000000111 !
b11000 %
b11110 $
b11100 #
1"
#1050
b0 I
0"
#1055
b10000011100110011110100000000111 9
0&
b111101100000111111001101111011 !
b1111 %
b10010 $
b1100 #
1"
#1060
b11100010010011010010110011000100 I
0"
#1065
1&
b10000011100111110000100000000111 !
b111 %
b11101 $
b1110 #
1"
#1070
b1001010010110110000100010010 I
0"
#1075
b10000011100111110000100000000111 E
0&
b10011100110101111101100000111001 !
b1101 %
b11001 $
b10010 #
1"
#1080
b1111011011111001001100111110110 I
b11100010010011010010110011000100 H
0"
#1085
1&
b1101111100000001001100111011111 !
b11111 %
b1010 $
b10100 #
1"
#1090
b0 I
b1011110011011000111110110111100 H
0"
#1095
b1101111100000001001100111011111 A
b10100000111100010001001001000001 !
b1 %
b1 $
b10101 #
1"
#1100
b10101110000110001100000101 H
0"
#1105
b10100000111100010001001001000001 )
b11011010000110001111110010110100 !
b1101 %
b10011 $
b1 #
1"
#1110
b10100000111100010001001001000001 H
0"
#1115
b11011010000110001111110010110100 -
b1000000101001010010110110000001 !
b11011 %
b1011 $
b11001 #
1"
#1120
b1111011011111001001100111110110 H
0"
#1125
b1000000101001010010110110000001 <
0&
b1001010000011001010011110010100 !
b1011 %
b110 $
b1 #
1"
#1130
b10100000111100010001001001000001 H
0"
#1135
1&
b100111010101010000111101001110 !
b1101 %
b100 $
b1101 #
1"
#1140
b11011010000110001111110010110100 H
0"
#1145
b100111010101010000111101001110 -
0&
b10100111000110000100110001001110 !
b10000 %
b1110 $
b11000 #
1"
#1150
b10000011100110011110100000000111 H
0"
#1155
b1000010011001101111100010000 !
b100 %
b11100 $
b10111 #
1"
#1160
b10010101100011010010001000101011 H
0"
#1165
b1010101011110011101010110101010 !
b1 %
b1011 $
b10000 #
1"
#1170
b0 H
0"
#1175
1&
b10001100100001011001100100011 !
b101 %
b10 $
b0 #
1"
#1180
0"
#1185
b10001100100001011001100100011 C
b11011010111100000001100110110 !
b1111 %
b11100 $
b10111 #
1"
#1190
b10010101100011010010001000101011 H
0"
#1195
b11011010111100000001100110110 /
0&
b10001110011000010011001000011100 !
b10000 $
b10000 #
1"
#1200
b0 H
0"
#1205
b10011110111000001100100100111 !
b11101 %
b10110 $
b111 #
1"
#1210
b10111000010000101100011001110000 I
b10000011100111110000100000000111 H
0"
#1215
1&
b10010100001000110001000000101000 !
b11110 %
b11101 $
b1010 #
1"
#1220
b1001010010110110000100010010 I
b0 H
0"
#1225
b10010100001000110001000000101000 @
0&
b1110111000010001111100011101 !
b10111 %
b101 $
b0 #
1"
#1230
b10001100100001011001100100011 I
0"
#1235
b11111101110001000011111011111011 !
b11110 %
b11000 $
b10101 #
1"
#1240
b10000011100110011110100000000111 I
b10101110000110001100000101 H
0"
#1245
b1011001101100011010110110110011 !
b1010 %
b10011 $
b1110 #
1"
#1250
b0 I
b0 H
0"
#1255
1&
b1010110111111110110111110101101 !
b111 %
b10101 $
b10111 #
1"
#1260
b10101110000110001100000101 I
b10010101100011010010001000101011 H
0"
#1265
b1010110111111110110111110101101 E
b11100010010011110001111011000100 !
b101 %
b10111 $
b0 #
1"
#1270
b10010101100011010010001000101011 I
b0 H
0"
#1275
b11100010010011110001111011000100 C
0&
b111010111101000011010101110101 !
b10011 %
b1000 $
b10001 #
1"
#1280
b1101001111111001001111111010011 I
b11110000101011111011000011100001 H
0"
#1285
b1000001000010011100001110000010 !
b10 %
b10001 $
b11100 #
1"
#1290
b11110000101011111011000011100001 I
b0 H
0"
#1295
b1110001010010110110010111100010 !
b1 %
b11001 $
b11001 #
1"
#1300
b1111011011111001001100111110110 I
b1111011011111001001100111110110 H
0"
#1305
1&
b1111111111000000000100111111111 !
b10111 %
b10000 $
b1 #
1"
#1310
b0 I
b10100000111100010001001001000001 H
0"
#1315
b1111111111000000000100111111111 8
1'
0&
b11111011100011001100101011110111 !
b1111 %
b10110 $
b11110 #
1"
#1320
b10111000010000101100011001110000 I
b10010100001000110001000000101000 H
0"
#1325
b0 A
b0 @
b0 >
b0 <
b0 ;
b0 :
b0 9
b0 8
b0 7
b0 6
b0 5
b0 2
b0 1
b0 /
b0 -
b0 F
b0 E
b0 C
b0 )
0'
b11111011000000100000110011110110 !
b11000 %
b11000 $
b1101 #
b100000 J
1"
#1330
b0 I
b0 H
0"
#1335
b11111111010001101110111011111110 !
b10110 %
b11001 $
1"
#1340
0"
#1345
b11100010101111010100001011000101 !
b10111 %
b10010 $
b1 #
1"
#1350
0"
#1355
b11001001010011001101110010010010 !
b11011 %
b11100 $
b11000 #
1"
#1360
0"
#1365
1&
b11101110000111100011100011011100 !
b11101 %
b10 $
b10011 #
1"
#1370
0"
#1375
b11101110000111100011100011011100 >
b1000111010111000100110110001110 !
b11111 %
b11011 $
b10111 #
1"
#1380
0"
#1385
b1000111010111000100110110001110 A
0&
b1011010000101000011010110110100 !
b10111 %
b10011 $
b11100 #
1"
#1390
0"
#1395
b10101100001010101101010001011000 !
b10011 %
b1101 $
b1101 #
1"
#1400
0"
#1405
b1110001001100100001110111100010 !
b10 %
b1001 $
b1001 #
1"
#1410
0"
#1415
b1000011111010101011101110000111 !
b11100 %
b1100 $
b10000 #
1"
#1420
0"
#1425
b100111101100110010110101001111 !
b11 %
b11101 $
b10010 #
1"
#1430
b11101110000111100011100011011100 I
0"
#1435
b1000111001100100011100010001 !
b1101 %
b10100 $
b11110 #
1"
#1440
b0 I
0"
#1445
1&
b10000101011111110101100000001010 !
b1 %
b11100 $
b1100 #
1"
#1450
0"
#1455
b10000101011111110101100000001010 )
b1010011100010101101011110100111 !
b10110 %
b1100 $
b1 #
1"
#1460
b10000101011111110101100000001010 H
0"
#1465
b1010011100010101101011110100111 7
0&
b11011001001100010100000010110010 !
b11011 %
b10111 $
b10000 #
1"
#1470
b0 H
0"
#1475
b1101111100010001100100111011111 !
b10100 %
b0 $
b10010 #
1"
#1480
0"
#1485
b101100000111000000001101011000 !
b1100 $
b110 #
1"
#1490
0"
#1495
b100011101101101111010101000111 !
b10101 %
b10110 $
b10110 #
1"
#1500
b1010011100010101101011110100111 I
b1010011100010101101011110100111 H
0"
#1505
1&
b11001010011000001000100010010100 !
b11011 %
b11111 $
b10101 #
1"
#1510
b1000111010111000100110110001110 I
b0 H
0"
#1515
b11001010011000001000100010010100 <
1'
b10000011010000000100101000000110 !
b10010 %
b10000 $
b1100 #
1"
#1520
b0 I
0"
#1525
b10000011010000000100101000000110 2
0'
0&
b11100100110010010110110011001001 !
b10 %
b1111 $
b11111 #
1"
#1530
b1000111010111000100110110001110 H
0"
#1535
b1001100000110111000101110011000 !
b1011 %
b1011 $
b11001 #
1"
#1540
b0 H
0"
#1545
b1110001010111111011100111100010 !
b10101 %
b10001 $
b10010 #
1"
#1550
b10000011010000000100101000000110 H
0"
#1555
b11010100100010111111111010101001 !
b10110 %
b11000 $
b1100 #
1"
#1560
b0 H
0"
#1565
b1111001111000001101100011110 !
b1100 %
b1011 $
1"
#1570
0"
#1575
1&
b11100010011101010111100011000100 !
b1010 %
b11001 $
b11010 #
1"
#1580
0"
#1585
b11100010011101010111100011000100 *
b10000001101011110100000000000011 !
b10101 %
b10010 $
b11001 #
1"
#1590
b10000011010000000100101000000110 I
0"
#1595
b10000001101011110100000000000011 6
0&
b111010101000011110011101110101 !
b10 %
b1100 $
b11010 #
1"
#1600
b0 I
0"
#1605
b1111001111101011001001111110011 !
b1011 %
b110 $
b10001 #
1"
#1610
0"
#1615
b10111010111000111000000001110101 !
b10100 %
b1000 $
b1000 #
1"
#1620
0"
#1625
b111011010101000001100101110110 !
b1011 %
b10110 $
b10001 #
1"
#1630
b1010011100010101101011110100111 I
0"
#1635
1&
b1111110001000101111110111111100 !
b110 %
b11100 $
b11010 #
1"
#1640
b0 I
0"
#1645
b1111110001000101111110111111100 D
0&
b1101111111100011110110111011111 !
b10 %
b1001 $
b10 #
1"
#1650
0"
#1655
b11010011010000001000000010100110 !
b1011 %
b1101 $
b10010 #
1"
#1660
b10000011010000000100101000000110 H
0"
#1665
b11001111100110101000000010011111 !
b11010 %
b10000 $
b100 #
1"
#1670
b0 H
0"
#1675
1&
b11101101110111000010110011011011 !
b1101 %
b111 $
b10101 #
1"
#1680
b10000001101011110100000000000011 H
0"
